roleplay/__init__.py
roleplay/util.py
roleplay/core/__init__.py
roleplay/core/llm.py
roleplay/core/memory.py
roleplay/core/parse.py
roleplay/core/role.py
roleplay/core/tool.py
roleplay/memory/__init__.py
roleplay/memory/limit.py
roleplay/memory/role.py
roleplay/stream/__init__.py
roleplay/stream/role.py
langchain_roleplay-0.0.3.dist-info/LICENSE
langchain_roleplay-0.0.3.dist-info/METADATA
langchain_roleplay-0.0.3.dist-info/WHEEL
langchain_roleplay-0.0.3.dist-info/top_level.txt
langchain_roleplay-0.0.3.dist-info/RECORD
