Metadata-Version: 2.2
Name: langchain-roleplay
Version: 0.0.3
Summary: A utility for reading configurations from a YAML file to run Langchain.
Author-email: maye76 <hi@maye.run>
License: MIT
Classifier: Programming Language :: Python :: 3
Classifier: License :: OSI Approved :: MIT License
License-File: LICENSE
Requires-Dist: langchain>=0.3.19
Requires-Dist: pydantic>=2.10.6
Requires-Dist: PyYAML>=6.0.2
Requires-Dist: langchain-openai>=0.3.7
